bnaug/__init__.py
bnaug/randaug.py
bnaug/sentence.py
bnaug/util.py
bnaug-1.1.2.dist-info/METADATA
bnaug-1.1.2.dist-info/WHEEL
bnaug-1.1.2.dist-info/top_level.txt
bnaug-1.1.2.dist-info/RECORD
