Metadata-Version: 2.1
Name: bnaug
Version: 1.1.2
Summary: bnaug is a text augmentation tool for Bangla text.
Home-page: https://github.com/sagorbrur/bnaug
Author: Sagor Sarker
Author-email: sagorhem3532@gmail.com
License: MIT
Classifier: Programming Language :: Python :: 3
Classifier: License :: OSI Approved :: MIT License
Classifier: Operating System :: OS Independent
Requires-Python: >=3.7
Requires-Dist: bnlp-toolkit ==3.3.2
Requires-Dist: transformers ==4.24.0
